pyseas/__init__.py
pyseas/seas.py
tests/__init__.py
tests/test_seas.py
pyseas-0.6.dist-info/LICENSE
pyseas-0.6.dist-info/METADATA
pyseas-0.6.dist-info/WHEEL
pyseas-0.6.dist-info/top_level.txt
pyseas-0.6.dist-info/RECORD
