Metadata-Version: 2.1
Name: pyseas
Version: 0.6
Summary: A Python wrapper for seas-nve API
Home-page: https://github.com/scaarup/pyseas
Author: Søren Christian Aarup
Author-email: sc@aarup.org
License: UNKNOWN
Platform: UNKNOWN
Classifier: Programming Language :: Python :: 3
Classifier: License :: OSI Approved :: MIT License
Classifier: Operating System :: OS Independent
Requires-Python: >=3
Requires-Dist: requests (>=2.0)
